datadis_client/__init__.py
datadis_client/consumption.py
datadis_client/search.py
datadis_client/supplies.py
python_datadis-0.0.1.dist-info/licenses/LICENSE
python_datadis-0.0.1.dist-info/METADATA
python_datadis-0.0.1.dist-info/WHEEL
python_datadis-0.0.1.dist-info/top_level.txt
python_datadis-0.0.1.dist-info/RECORD
