Metadata-Version: 2.4
Name: python-datadis
Version: 0.0.1
Summary: A Python client for the Datadis API.
Author-email: agaliste <me@agaliste.dev>
Project-URL: Homepage, https://github.com/agaliste/python-datadis
Project-URL: Bug Tracker, https://github.com/agaliste/python-datadis/issues
Classifier: Programming Language :: Python :: 3
Classifier: License :: OSI Approved :: MIT License
Classifier: Operating System :: OS Independent
Requires-Python: >=3.8
License-File: LICENSE
Requires-Dist: requests>=2.32.3
Provides-Extra: dev
Requires-Dist: pytest>=8.3.5; extra == "dev"
Requires-Dist: pytest-cov>=6.1.1; extra == "dev"
Requires-Dist: python-dotenv>=1.1.0; extra == "dev"
Dynamic: license-file
